LICENSE
README.md
setup.cfg
setup.py
pylivedev/__init__.py
pylivedev/__main__.py
pylivedev/app.py
pylivedev/imports.py
pylivedev/output.py
pylivedev/version.py
pylivedev.egg-info/PKG-INFO
pylivedev.egg-info/SOURCES.txt
pylivedev.egg-info/dependency_links.txt
pylivedev.egg-info/entry_points.txt
pylivedev.egg-info/requires.txt
pylivedev.egg-info/top_level.txt
pylivedev.egg-info/zip-safe