Metadata-Version: 2.1
Name: pylivedev
Version: 1.2.1
Summary: PyLiveDev is used to keep track of files associated with your script so it can be re-started if any file is updated.
Home-page: https://ouroboroscoding.com/pylivedev
Author: Chris Nasr - OuroborosCoding
Author-email: chris@ouroboroscoding.com
License: Apache-2.0
Project-URL: Source, https://github.com/ouroboroscoding/pylivedev
Project-URL: Tracker, https://github.com/ouroboroscoding/pylivedev/issues
Keywords: python,live,development
Platform: UNKNOWN
License-File: LICENSE
